setup.py
DeCAF.egg-info/PKG-INFO
DeCAF.egg-info/SOURCES.txt
DeCAF.egg-info/dependency_links.txt
DeCAF.egg-info/requires.txt
DeCAF.egg-info/top_level.txt
decaf/__init__.py
decaf/utils.py
decaf/toolkits/__init__.py
decaf/toolkits/ob.py
decaf/toolkits/rd.py
tests/__init__.py
tests/decaf_test.py
tests/utils_test.py