Metadata-Version: 1.0
Name: DeCAF
Version: 2.0.0
Summary: Discrimination, Comparison, Alignment tool for small molecules
Home-page: https://bitbucket.org/marta-sd/decaf
Author: Marta M. Stepniewska
Author-email: martasd@ibb.waw.pl
License: BSD
Keywords: cheminformatics,small molecules,pharmacophore,graph,alignment
Platform: UNKNOWN
